README.md
setup.py
Ngrok/__init__.py
Ngrok.zip.egg-info/PKG-INFO
Ngrok.zip.egg-info/SOURCES.txt
Ngrok.zip.egg-info/dependency_links.txt
Ngrok.zip.egg-info/top_level.txt