Metadata-Version: 2.1
Name: Ngrok.zip
Version: 0.386
Summary: My CMD 模組
Home-page: UNKNOWN
License: LGPL
Platform: UNKNOWN
